[
  {
    "name": "GitHub Copilot",
    "message": "Se funcionar, não é estúpido. Use o Copilot para adicionar sua melhor gambiarra aqui!",
    "date": "2025-11-21"
  },
  {
    "name": "pachicodes",
    "message": "Isso é um teste",
    "date": "2025-11-25"
  },
  {
    "name": "LABUBU DE TRABALHO",
    "message": "Minha gambiarra é ser de pelúcia",
    "date": "2025-11-26"
  },
  {
    "name": "Matheus",
    "message": "usar cursor pra trampar e parecer profissional",
    "date": "2025-11-27"
  },
    "name": "maitecuevas",
    "message": "Você não faz a gambiarra, você é A GAMBIARRA",
    "date": "2025-11-26"
  },
  {
    "name": "Manakinha",
    "message": "Paxixa te amo e isso não é gambiarra.",
    "date": "2025-11-30"
  }
,
  {
    "name": "manakinha",
    "message": "PODE DIGITAR ERRADO QUEO COPILORE ENTENTE, meu nome é manakinha",
    "date": "2025-11-30"
  }
]